trezorcrypto.cpython-36m-darwin.so
TrezorCrypto-0.0.6.dist-info/AUTHORS
TrezorCrypto-0.0.6.dist-info/LICENSE
TrezorCrypto-0.0.6.dist-info/METADATA
TrezorCrypto-0.0.6.dist-info/WHEEL
TrezorCrypto-0.0.6.dist-info/top_level.txt
TrezorCrypto-0.0.6.dist-info/RECORD
