Metadata-Version: 2.1
Name: TrezorCrypto
Version: 0.0.6
Summary: Cython wrapper around trezor-crypto library
Home-page: https://github.com/zebra-lucky/trezor-crypto
Author: UNKNOWN
Author-email: UNKNOWN
License: MIT
Platform: UNKNOWN
Classifier: License :: OSI Approved :: MIT License
Classifier: Operating System :: POSIX :: Linux
Classifier: Operating System :: Microsoft :: Windows
Classifier: Operating System :: MacOS :: MacOS X
Classifier: Programming Language :: Python :: 3 :: Only
